et/__init__.py
et/client.py
et/codecs.py
et/server.py
et-0.0.2.dist-info/DESCRIPTION.rst
et-0.0.2.dist-info/METADATA
et-0.0.2.dist-info/RECORD
et-0.0.2.dist-info/WHEEL
et-0.0.2.dist-info/metadata.json
et-0.0.2.dist-info/top_level.txt
et-0.0.2.dist-info/zip-safe
