Metadata-Version: 1.0
Name: et
Version: 0.0.2
Summary: Simple package to phone home by sending and receiving arbitrary dictionaries via UDP  
Home-page: https://github.com/reece/et
Author: See https://github.com/reece/et
Author-email: reecehart@gmail.com
License: UNKNOWN
Platform: UNKNOWN
